serveml/__init__.py
serveml/api.py
serveml/inputs.py
serveml/loader.py
serveml/outputs.py
serveml/predictions.py
serveml/utils.py
serveml-0.3.0.dist-info/LICENSE
serveml-0.3.0.dist-info/METADATA
serveml-0.3.0.dist-info/WHEEL
serveml-0.3.0.dist-info/top_level.txt
serveml-0.3.0.dist-info/RECORD
