Metadata-Version: 2.1
Name: serveml
Version: 0.3.0
Summary: serveml is a machine learning serving tool
Home-page: http://github.com/gfalcone/mlserve
Author: gfalcone
Author-email: gfalcone@github.com
License: Apache
Platform: UNKNOWN
Classifier: Programming Language :: Python :: 3
Classifier: License :: OSI Approved :: Apache Software License
Classifier: Operating System :: OS Independent
Requires-Python: >=3.6
Requires-Dist: mlflow[extras] (>=1.6.0)
Requires-Dist: fastapi (==0.52.0)
Requires-Dist: uvicorn (==0.11.3)
